pharaoh/__init__.py
pharaoh/__main__.py
pharaoh/api.py
pharaoh/cli.py
pharaoh/errors.py
pharaoh/log.py
pharaoh/project.py
pharaoh/sphinx_app.py
pharaoh/version.py
pharaoh/assetlib/__init__.py
pharaoh/assetlib/api.py
pharaoh/assetlib/catch_exceptions.py
pharaoh/assetlib/context.py
pharaoh/assetlib/finder.py
pharaoh/assetlib/generation.py
pharaoh/assetlib/matlab_engine.py
pharaoh/assetlib/resource.py
pharaoh/assetlib/util.py
pharaoh/assetlib/patches/.gitignore
pharaoh/assetlib/patches/__init__.py
pharaoh/assetlib/patches/_bokeh.py
pharaoh/assetlib/patches/_holoviews.py
pharaoh/assetlib/patches/_matplotlib.py
pharaoh/assetlib/patches/_pandas.py
pharaoh/assetlib/patches/_panel.py
pharaoh/assetlib/patches/_plotly.py
pharaoh/assetlib/patches/bokeh_embed.html
pharaoh/plugins/__init__.py
pharaoh/plugins/api.py
pharaoh/plugins/contextvar.py
pharaoh/plugins/plugin_manager.py
pharaoh/plugins/spec.py
pharaoh/plugins/template.py
pharaoh/plugins/core_plugin/__init__.py
pharaoh/plugins/core_plugin/default_settings.yaml
pharaoh/plugins/core_plugin/plugin.py
pharaoh/plugins/core_plugin/asset_templates/datatable.rst.jinja2
pharaoh/plugins/core_plugin/asset_templates/error.rst.jinja2
pharaoh/plugins/core_plugin/asset_templates/error_traceback.rst.jinja2
pharaoh/plugins/core_plugin/asset_templates/iframe.rst.jinja2
pharaoh/plugins/core_plugin/asset_templates/image.rst.jinja2
pharaoh/plugins/core_plugin/asset_templates/include_wrapper.rst.jinja2
pharaoh/plugins/core_plugin/asset_templates/markdown.rst.jinja2
pharaoh/plugins/core_plugin/asset_templates/raw_html.rst.jinja2
pharaoh/plugins/core_plugin/asset_templates/raw_rst.rst.jinja2
pharaoh/plugins/core_plugin/asset_templates/raw_txt.rst.jinja2
pharaoh/plugins/core_plugin/level_1/__init__.py
pharaoh/plugins/core_plugin/level_1/empty/.gitignore
pharaoh/plugins/core_plugin/level_1/empty/default_context.yaml
pharaoh/plugins/core_plugin/level_1/empty/index.rst
pharaoh/plugins/core_plugin/level_1/empty/asset_scripts/default_assets.py
pharaoh_report-0.9.4.dist-info/METADATA
pharaoh_report-0.9.4.dist-info/WHEEL
pharaoh_report-0.9.4.dist-info/entry_points.txt
pharaoh_report-0.9.4.dist-info/licenses/LICENSE.txt
pharaoh_report-0.9.4.dist-info/RECORD
